{"role_name": "小果冻儿_XiaoGuoDongEr", "url": "https://www.xsnvshen.com/girl/28069", "online_total": 42, "album": {"000": {"folder_name": "[MFStar]高清写真图 2020.09.07 VOL.382 小果冻儿jelly模范学院浴缸内衣 小果冻儿jelly女神私房照_秀色女神", "image_num": 60, "album_url": "https://www.xsnvshen.com/album/34177", "index": "000", "harf_link": "https://img.xsnvshen.com/album/28069/34177/"}, "001": {"folder_name": "[MFStar]高清写真图 2020.09.15 VOL.386 小果冻儿模范学院可爱制服 小果冻儿jelly女神私房照_秀色女神", "image_num": 47, "album_url": "https://www.xsnvshen.com/album/34230", "index": "001", "harf_link": "https://img.xsnvshen.com/album/28069/34230/"}, "002": {"folder_name": "[FEILIN]高清写真图 2020.12.31 No.363 小果冻儿嗲囡囡制服黑丝 小果冻儿jelly女神私房照_秀色女神", "image_num": 28, "album_url": "https://www.xsnvshen.com/album/34992", "index": "002", "harf_link": "https://img.xsnvshen.com/album/28069/34992/"}, "003": {"folder_name": "[XiuRen]高清写真图 2021.01.11 No.2988 小果冻儿秀人网可爱美腿 小果冻儿jelly女神私房照_秀色女神", "image_num": 55, "album_url": "https://www.xsnvshen.com/album/35067", "index": "003", "harf_link": "https://img.xsnvshen.com/album/28069/35067/"}, "004": {"folder_name": "[MFStar]高清写真图 2021.01.14 VOL.439 小果冻儿模范学院可爱制服黑丝 小果冻儿jelly女神私房照_秀色女神", "image_num": 48, "album_url": "https://www.xsnvshen.com/album/35145", "index": "004", "harf_link": "https://img.xsnvshen.com/album/28069/35145/"}, "005": {"folder_name": "[XiuRen]高清写真图 2021.02.02 No.3070 小果冻儿秀人网双马尾可爱 小果冻儿jelly女神私房照_秀色女神", "image_num": 55, "album_url": "https://www.xsnvshen.com/album/35247", "index": "005", "harf_link": "https://img.xsnvshen.com/album/28069/35247/"}, "006": {"folder_name": "[MFStar]高清写真图 2021.01.26 VOL.447 小果冻儿模范学院制服丝袜 小果冻儿jelly女神私房照_秀色女神", "image_num": 39, "album_url": "https://www.xsnvshen.com/album/35270", "index": "006", "harf_link": "https://img.xsnvshen.com/album/28069/35270/"}, "007": {"folder_name": "[MFStar]高清写真图 2021.03.12 VOL.467 小果冻儿模范学院运动内衣 小果冻儿jelly女神私房照_秀色女神", "image_num": 42, "album_url": "https://www.xsnvshen.com/album/35548", "index": "007", "harf_link": "https://img.xsnvshen.com/album/28069/35548/"}, "008": {"folder_name": "[XiuRen]高清写真图 2021.04.23 VOL.3336 小果冻儿秀人网模范学院内衣黑丝 小果冻儿jelly女神私房照_秀色女神", "image_num": 50, "album_url": "https://www.xsnvshen.com/album/35908", "index": "008", "harf_link": "https://img.xsnvshen.com/album/28069/35908/"}, "009": {"folder_name": "[MFStar]高清写真图 2021.04.29 VOL.489 小果冻儿模范学院内衣性感 小果冻儿jelly女神私房照_秀色女神", "image_num": 48, "album_url": "https://www.xsnvshen.com/album/35970", "index": "009", "harf_link": "https://img.xsnvshen.com/album/28069/35970/"}, "010": {"folder_name": "[FEILIN]高清写真图 2021.05.19 VOL.390 小果冻儿嗲囡囡黑丝 小果冻儿jelly女神私房照_秀色女神", "image_num": 40, "album_url": "https://www.xsnvshen.com/album/36088", "index": "010", "harf_link": "https://img.xsnvshen.com/album/28069/36088/"}, "011": {"folder_name": "[XiuRen]高清写真图 2021.06.03 VOL.3500 小果冻儿秀人网湿身 小果冻儿jelly女神私房照_秀色女神", "image_num": 62, "album_url": "https://www.xsnvshen.com/album/36191", "index": "011", "harf_link": "https://img.xsnvshen.com/album/28069/36191/"}, "012": {"folder_name": "可爱少女小果冻儿 体操服运动香汗湿身秀人网可爱湿身 小果冻儿jelly女神私房照_秀色女神", "image_num": 62, "album_url": "https://www.xsnvshen.com/album/36321", "index": "012", "harf_link": "https://img.xsnvshen.com/album/28069/36321/"}, "013": {"folder_name": "小果冻儿卡哇伊 居家饲养人畜无害秀人网可爱 小果冻儿jelly女神私房照_秀色女神", "image_num": 60, "album_url": "https://www.xsnvshen.com/album/36572", "index": "013", "harf_link": "https://img.xsnvshen.com/album/28069/36572/"}, "014": {"folder_name": "小果冻儿卡哇伊 居家饲养捆绑约束秀人网可爱 小果冻儿jelly女神私房照_秀色女神", "image_num": 62, "album_url": "https://www.xsnvshen.com/album/36989", "index": "014", "harf_link": "https://img.xsnvshen.com/album/28069/36989/"}, "015": {"folder_name": "[XiuRen]高清写真图 2021.09.24 No.3988 小果冻儿秀人网可爱角色扮演 小果冻儿jelly女神私房照_秀色女神", "image_num": 54, "album_url": "https://www.xsnvshen.com/album/37129", "index": "015", "harf_link": "https://img.xsnvshen.com/album/28069/37129/"}, "016": {"folder_name": "[XiuRen]高清写真图 2021.10.09 No.4036 小果冻儿秀人网可爱瑜伽服 小果冻儿jelly女神私房照_秀色女神", "image_num": 56, "album_url": "https://www.xsnvshen.com/album/37237", "index": "016", "harf_link": "https://img.xsnvshen.com/album/28069/37237/"}, "017": {"folder_name": "[FEILIN]高清写真图 2021.10.28 VOL.417 小果冻儿嗲囡囡可爱黑丝性感制服 小果冻儿jelly女神私房照_秀色女神", "image_num": 70, "album_url": "https://www.xsnvshen.com/album/37377", "index": "017", "harf_link": "https://img.xsnvshen.com/album/28069/37377/"}, "018": {"folder_name": "[XiuRen]高清写真图 2021.10.25 No.4108 小果冻儿秀人网双马尾可爱养眼 小果冻儿jelly女神私房照_秀色女神", "image_num": 40, "album_url": "https://www.xsnvshen.com/album/37388", "index": "018", "harf_link": "https://img.xsnvshen.com/album/28069/37388/"}, "019": {"folder_name": "[XiuRen]高清写真图 2021.11.22 No.4245 小果冻儿秀人网可爱黑丝 小果冻儿jelly女神私房照_秀色女神", "image_num": 60, "album_url": "https://www.xsnvshen.com/album/37637", "index": "019", "harf_link": "https://img.xsnvshen.com/album/28069/37637/"}, "020": {"folder_name": "[XiuRen]高清写真图 2021.12.06 No.4300 小果冻儿秀人网圣诞可爱性感 小果冻儿jelly女神私房照_秀色女神", "image_num": 57, "album_url": "https://www.xsnvshen.com/album/37791", "index": "020", "harf_link": "https://img.xsnvshen.com/album/28069/37791/"}, "021": {"folder_name": "[XiuRen]高清写真图 2022.02.07 No.4546 小果冻儿秀人网空姐制服内衣黑丝性感 小果冻儿jelly女神私房照_秀色女神", "image_num": 86, "album_url": "https://www.xsnvshen.com/album/38126", "index": "021", "harf_link": "https://img.xsnvshen.com/album/28069/38126/"}, "022": {"folder_name": "[XiuRen]高清写真图 2022.02.24 No.4625 小果冻儿秀人网空姐制服内衣黑丝性感 小果冻儿jelly女神私房照_秀色女神", "image_num": 76, "album_url": "https://www.xsnvshen.com/album/38295", "index": "022", "harf_link": "https://img.xsnvshen.com/album/28069/38295/"}, "023": {"folder_name": "[MFStar]高清写真图 2022.02.28 VOL.553 小果冻儿模范学院内衣黑丝性感气质清纯 小果冻儿jelly女神私房照_秀色女神", "image_num": 47, "album_url": "https://www.xsnvshen.com/album/38349", "index": "023", "harf_link": "https://img.xsnvshen.com/album/28069/38349/"}, "024": {"folder_name": "[XiuRen]高清写真图 2022.03.16 No.4726 小果冻儿秀人网双马尾性感内衣丝袜 小果冻儿jelly女神私房照_秀色女神", "image_num": 82, "album_url": "https://www.xsnvshen.com/album/38482", "index": "024", "harf_link": "https://img.xsnvshen.com/album/28069/38482/"}, "025": {"folder_name": "[XiuRen]高清写真图 2022.03.29 No.4789 小果冻儿秀人网性感内衣黑丝 小果冻儿jelly女神私房照_秀色女神", "image_num": 65, "album_url": "https://www.xsnvshen.com/album/38550", "index": "025", "harf_link": "https://img.xsnvshen.com/album/28069/38550/"}, "026": {"folder_name": "[XiuRen]高清写真图 2022.04.06 No.4828 小果冻儿秀人网性感黑丝 小果冻儿jelly女神私房照_秀色女神", "image_num": 69, "album_url": "https://www.xsnvshen.com/album/38591", "index": "026", "harf_link": "https://img.xsnvshen.com/album/28069/38591/"}, "027": {"folder_name": "[XiuRen]高清写真图 2022.04.28 No.4942 小果冻儿秀人网可爱丝袜性感 小果冻儿jelly女神私房照_秀色女神", "image_num": 75, "album_url": "https://www.xsnvshen.com/album/38777", "index": "027", "harf_link": "https://img.xsnvshen.com/album/28069/38777/"}, "028": {"folder_name": "[XiuRen]高清写真图 2022.05.30 No.5075 小果冻儿秀人网性感内衣丝袜 小果冻儿jelly女神私房照_秀色女神", "image_num": 65, "album_url": "https://www.xsnvshen.com/album/38949", "index": "028", "harf_link": "https://img.xsnvshen.com/album/28069/38949/"}, "029": {"folder_name": "[XiuRen]高清写真图 2022.06.13 No.5136 小果冻儿秀人网性感内衣丝袜制服诱惑 小果冻儿jelly女神私房照_秀色女神", "image_num": 68, "album_url": "https://www.xsnvshen.com/album/39048", "index": "029", "harf_link": "https://img.xsnvshen.com/album/28069/39048/"}, "030": {"folder_name": "[XiuRen]高清写真图 2022.07.11 No.5256 小果冻儿秀人网和服骨感性感 小果冻儿jelly女神私房照_秀色女神", "image_num": 42, "album_url": "https://www.xsnvshen.com/album/39232", "index": "030", "harf_link": "https://img.xsnvshen.com/album/28069/39232/"}, "031": {"folder_name": "[MFStar]高清写真图 2022.07.18 VOL.564 小果冻儿模范学院黑丝性感气质清纯 小果冻儿jelly女神私房照_秀色女神", "image_num": 39, "album_url": "https://www.xsnvshen.com/album/39283", "index": "031", "harf_link": "https://img.xsnvshen.com/album/28069/39283/"}, "032": {"folder_name": "[XiuRen]高清写真图 2022.07.22 No.5318 小果冻儿秀人网性感丝袜 小果冻儿jelly女神私房照_秀色女神", "image_num": 60, "album_url": "https://www.xsnvshen.com/album/39292", "index": "032", "harf_link": "https://img.xsnvshen.com/album/28069/39292/"}, "033": {"folder_name": "[XiuRen]高清写真图 2022.07.27 No.5344 小果冻儿秀人网骨感丝袜大尺度性感 小果冻儿jelly女神私房照_秀色女神", "image_num": 76, "album_url": "https://www.xsnvshen.com/album/39328", "index": "033", "harf_link": "https://img.xsnvshen.com/album/28069/39328/"}, "034": {"folder_name": "[XiuRen]高清写真图 2022.08.02 No.5369 小果冻儿秀人网性感黑丝 小果冻儿jelly女神私房照_秀色女神", "image_num": 41, "album_url": "https://www.xsnvshen.com/album/39355", "index": "034", "harf_link": "https://img.xsnvshen.com/album/28069/39355/"}, "035": {"folder_name": "[XiuRen]高清写真图 2022.08.16 No.5443 小果冻儿秀人网双马尾可爱内衣性感 小果冻儿jelly女神私房照_秀色女神", "image_num": 92, "album_url": "https://www.xsnvshen.com/album/39462", "index": "035", "harf_link": "https://img.xsnvshen.com/album/28069/39462/"}, "036": {"folder_name": "[XiuRen]高清写真图 2022.08.19 No.5463 小果冻儿秀人网可爱双马尾运动性感 小果冻儿jelly女神私房照_秀色女神", "image_num": 46, "album_url": "https://www.xsnvshen.com/album/39503", "index": "036", "harf_link": "https://img.xsnvshen.com/album/28069/39503/"}, "037": {"folder_name": "[XiuRen]高清写真图 2022.09.06 No.5548 小果冻儿秀人网双马尾比基尼性感 小果冻儿jelly女神私房照_秀色女神", "image_num": 57, "album_url": "https://www.xsnvshen.com/album/39549", "index": "037", "harf_link": "https://img.xsnvshen.com/album/28069/39549/"}, "038": {"folder_name": "[XiuRen]高清写真图 2022.09.20 No.5611 小果冻儿秀人网比基尼性感 小果冻儿jelly女神私房照_秀色女神", "image_num": 27, "album_url": "https://www.xsnvshen.com/album/39670", "index": "038", "harf_link": "https://img.xsnvshen.com/album/28069/39670/"}, "039": {"folder_name": "[XiuRen]高清写真图 2023.04.03 No.6516 小果冻儿 黑丝美腿秀人网性感美腿内衣黑丝 小果冻儿jelly女神私房照_秀色女神", "image_num": 79, "album_url": "https://www.xsnvshen.com/album/40807", "index": "039", "harf_link": "https://img.xsnvshen.com/album/28069/40807/"}, "040": {"folder_name": "[XiuRen]高清写真图 2023.04.10 No.6549 小果冻儿 丝袜美腿秀人网性感美腿内衣 小果冻儿jelly女神私房照_秀色女神", "image_num": 74, "album_url": "https://www.xsnvshen.com/album/40843", "index": "040", "harf_link": "https://img.xsnvshen.com/album/28069/40843/"}, "041": {"folder_name": "[XiuRen]高清写真图 2023.05.24 No.6795 小果冻儿 黑丝美腿秀人网性感女仆美腿黑丝 小果冻儿jelly女神私房照_秀色女神", "image_num": 86, "album_url": "https://www.xsnvshen.com/album/41191", "index": "041", "harf_link": "https://img.xsnvshen.com/album/28069/41191/"}}}