{"role_name": "玛鲁娜_Manuela", "url": "https://www.xsnvshen.com/girl/20625", "online_total": 59, "album": {"000": {"folder_name": "玛鲁娜Manuela(汤曼玲) [MyGirl美媛馆]高清写真图2015.03.25 Vol.107极品美臀大尺度制服诱惑 玛鲁娜女神私房照_秀色女神", "image_num": 50, "album_url": "https://www.xsnvshen.com/album/13558", "index": "000", "harf_link": "https://img.xsnvshen.com/album/20625/13558/"}, "001": {"folder_name": "玛鲁娜Manuela(汤曼玲) [MyGirl美媛馆]高清写真图2015.04.01 Vol.111极品美臀大尺度 玛鲁娜女神私房照_秀色女神", "image_num": 72, "album_url": "https://www.xsnvshen.com/album/13559", "index": "001", "harf_link": "https://img.xsnvshen.com/album/20625/13559/"}, "002": {"folder_name": "玛鲁娜Manuela(汤曼玲) [MyGirl美媛馆]高清写真图2015.04.08 Vol.114家居性感美臀 玛鲁娜女神私房照_秀色女神", "image_num": 61, "album_url": "https://www.xsnvshen.com/album/14494", "index": "002", "harf_link": "https://img.xsnvshen.com/album/20625/14494/"}, "003": {"folder_name": "玛鲁娜 [MFStar模范学院]高清写真图VOL.004性感美臀诱惑 玛鲁娜女神私房照_秀色女神", "image_num": 48, "album_url": "https://www.xsnvshen.com/album/14638", "index": "003", "harf_link": "https://img.xsnvshen.com/album/20625/14638/"}, "004": {"folder_name": "玛鲁娜 [秀人网美媛馆]高清写真图NO.329秀人网极品养眼内衣诱惑美臀 玛鲁娜女神私房照_秀色女神", "image_num": 56, "album_url": "https://www.xsnvshen.com/album/14677", "index": "004", "harf_link": "https://img.xsnvshen.com/album/20625/14677/"}, "005": {"folder_name": "玛鲁娜Manuela(汤曼玲) [MFStar模范学院]高清写真图VOL.007户外养眼 玛鲁娜女神私房照_秀色女神", "image_num": 46, "album_url": "https://www.xsnvshen.com/album/14750", "index": "005", "harf_link": "https://img.xsnvshen.com/album/20625/14750/"}, "006": {"folder_name": "玛鲁娜Manuela(汤曼玲) [XIUREN秀人网]高清写真图2015.06.04 XR20150604N00336秀人网家居尤物性感诱惑 玛鲁娜女神私房照_秀色女神", "image_num": 40, "album_url": "https://www.xsnvshen.com/album/16263", "index": "006", "harf_link": "https://img.xsnvshen.com/album/20625/16263/"}, "007": {"folder_name": "玛鲁娜Manuela(汤曼玲) [XIUREN秀人网]高清写真图2015.07.22 XR20150722N00359秀人网家居角色扮演性感诱惑 玛鲁娜女神私房照_秀色女神", "image_num": 41, "album_url": "https://www.xsnvshen.com/album/16320", "index": "007", "harf_link": "https://img.xsnvshen.com/album/20625/16320/"}, "008": {"folder_name": "玛鲁娜Manuela(汤曼玲) [XIUREN秀人网]高清写真图2015.07.28 XR20150728N00365秀人网家居角色扮演性感诱惑比基尼 玛鲁娜女神私房照_秀色女神", "image_num": 54, "album_url": "https://www.xsnvshen.com/album/17109", "index": "008", "harf_link": "https://img.xsnvshen.com/album/20625/17109/"}, "009": {"folder_name": "玛鲁娜Manuela(汤曼玲) [XIUREN秀人网]高清写真图2015.08.06 XR20150806N00372秀人网家居性感诱惑比基尼 玛鲁娜女神私房照_秀色女神", "image_num": 51, "album_url": "https://www.xsnvshen.com/album/17110", "index": "009", "harf_link": "https://img.xsnvshen.com/album/20625/17110/"}, "010": {"folder_name": "玛鲁娜Manuela(汤曼玲) [XIUREN秀人网]高清写真图2015.08.18 XR20150818N00380秀人网泳池美臀性感比基尼诱惑户外清新 玛鲁娜女神私房照_秀色女神", "image_num": 48, "album_url": "https://www.xsnvshen.com/album/17111", "index": "010", "harf_link": "https://img.xsnvshen.com/album/20625/17111/"}, "011": {"folder_name": "玛鲁娜Manuela [XIUREN秀人网]高清写真图2015.12.07 XR20151207N00433秀人网家居内衣美臀诱惑 玛鲁娜女神私房照_秀色女神", "image_num": 48, "album_url": "https://www.xsnvshen.com/album/17719", "index": "011", "harf_link": "https://img.xsnvshen.com/album/20625/17719/"}, "012": {"folder_name": "玛鲁娜Manuela [XIUREN秀人网]高清写真图2016.01.20 XR20160120N00464秀人网极品内衣美臀诱惑性感 玛鲁娜女神私房照_秀色女神", "image_num": 69, "album_url": "https://www.xsnvshen.com/album/17924", "index": "012", "harf_link": "https://img.xsnvshen.com/album/20625/17924/"}, "013": {"folder_name": "玛鲁娜Manuela [XIUREN秀人网]高清写真图2016.02.25 XR20160225N00487秀人网极品内衣美臀诱惑 玛鲁娜女神私房照_秀色女神", "image_num": 43, "album_url": "https://www.xsnvshen.com/album/18213", "index": "013", "harf_link": "https://img.xsnvshen.com/album/20625/18213/"}, "014": {"folder_name": "玛鲁娜Manuela [XIUREN秀人网]高清写真图2016.06.06 XR20160606N00536秀人网极品美臀诱惑 玛鲁娜女神私房照_秀色女神", "image_num": 50, "album_url": "https://www.xsnvshen.com/album/19269", "index": "014", "harf_link": "https://img.xsnvshen.com/album/20625/19269/"}, "015": {"folder_name": "玛鲁娜Manuela [XIUREN秀人网]高清写真图2016.07.01 XR20160701N00554秀人网美臀和服角色扮演性感 玛鲁娜女神私房照_秀色女神", "image_num": 47, "album_url": "https://www.xsnvshen.com/album/19542", "index": "015", "harf_link": "https://img.xsnvshen.com/album/20625/19542/"}, "016": {"folder_name": "玛鲁娜Manuela [XIUREN秀人网]高清写真图2016.08.03 XR20160803N00570秀人网美臀肉感 玛鲁娜女神私房照_秀色女神", "image_num": 48, "album_url": "https://www.xsnvshen.com/album/20256", "index": "016", "harf_link": "https://img.xsnvshen.com/album/20625/20256/"}, "017": {"folder_name": "玛鲁娜Manuela- [HuaYan花の颜] 2016.12.31 VOL.018美臀肉感 玛鲁娜女神私房照_秀色女神", "image_num": 48, "album_url": "https://www.xsnvshen.com/album/21709", "index": "017", "harf_link": "https://img.xsnvshen.com/album/20625/21709/"}, "018": {"folder_name": "玛鲁娜Manuela- [HuaYan花の颜]高清写真图 2017.01.23 VOL.023比基尼美臀 玛鲁娜女神私房照_秀色女神", "image_num": 53, "album_url": "https://www.xsnvshen.com/album/22017", "index": "018", "harf_link": "https://img.xsnvshen.com/album/20625/22017/"}, "019": {"folder_name": "玛鲁娜Manuela- [HuaYan花の颜]高清写真图 2017.02.15 VOL.028美臀比基尼湿身大尺度 玛鲁娜女神私房照_秀色女神", "image_num": 35, "album_url": "https://www.xsnvshen.com/album/22242", "index": "019", "harf_link": "https://img.xsnvshen.com/album/20625/22242/"}, "020": {"folder_name": "玛鲁娜Manuela- [HuaYan花の颜]高清写真图 2017.03.25 VOL.032美臀肉感大尺度马来西亚 玛鲁娜女神私房照_秀色女神", "image_num": 50, "album_url": "https://www.xsnvshen.com/album/22591", "index": "020", "harf_link": "https://img.xsnvshen.com/album/20625/22591/"}, "021": {"folder_name": "翘臀女神玛鲁娜 运动短装自行车足球宝贝美臀肉感比基尼内衣 玛鲁娜女神私房照_秀色女神", "image_num": 62, "album_url": "https://www.xsnvshen.com/album/22932", "index": "021", "harf_link": "https://img.xsnvshen.com/album/20625/22932/"}, "022": {"folder_name": "双马尾女神玛鲁娜 淡蓝粗布火辣事业性花の颜波涛胸涌美臀大尺度 玛鲁娜女神私房照_秀色女神", "image_num": 33, "album_url": "https://www.xsnvshen.com/album/23320", "index": "022", "harf_link": "https://img.xsnvshen.com/album/20625/23320/"}, "023": {"folder_name": "翘臀女教师玛鲁娜 制服诱惑厨娘系列花の颜波涛胸涌美臀制服诱惑 玛鲁娜女神私房照_秀色女神", "image_num": 50, "album_url": "https://www.xsnvshen.com/album/23856", "index": "023", "harf_link": "https://img.xsnvshen.com/album/20625/23856/"}, "024": {"folder_name": "双马尾美人玛鲁娜 开背毛衣与蜜桃臀花の颜开背毛衣美臀 玛鲁娜女神私房照_秀色女神", "image_num": 42, "album_url": "https://www.xsnvshen.com/album/24340", "index": "024", "harf_link": "https://img.xsnvshen.com/album/20625/24340/"}, "025": {"folder_name": "美尻美人玛鲁娜 日本学生妹制服模范学院校服美臀制服日本 玛鲁娜女神私房照_秀色女神", "image_num": 42, "album_url": "https://www.xsnvshen.com/album/28879", "index": "025", "harf_link": "https://img.xsnvshen.com/album/20625/28879/"}, "026": {"folder_name": "玛鲁娜的OL装扮 会心一击美臀诱惑模范学院美臀诱惑日本 玛鲁娜女神私房照_秀色女神", "image_num": 51, "album_url": "https://www.xsnvshen.com/album/29020", "index": "026", "harf_link": "https://img.xsnvshen.com/album/20625/29020/"}, "027": {"folder_name": "玛鲁娜的美臀诱惑 沙巴旅拍最后一套模范学院内衣美臀诱惑 玛鲁娜女神私房照_秀色女神", "image_num": 34, "album_url": "https://www.xsnvshen.com/album/29084", "index": "027", "harf_link": "https://img.xsnvshen.com/album/20625/29084/"}, "028": {"folder_name": "玛鲁娜的美臀诱惑 户外拍摄洛丽塔主题秀人网户外美臀诱惑 玛鲁娜女神私房照_秀色女神", "image_num": 45, "album_url": "https://www.xsnvshen.com/album/29318", "index": "028", "harf_link": "https://img.xsnvshen.com/album/20625/29318/"}, "029": {"folder_name": "玛鲁娜的美臀诱惑 白色镂空内衣湿身秀人网内衣湿身大尺度美臀诱惑 玛鲁娜女神私房照_秀色女神", "image_num": 43, "album_url": "https://www.xsnvshen.com/album/29410", "index": "029", "harf_link": "https://img.xsnvshen.com/album/20625/29410/"}, "030": {"folder_name": "玛鲁娜的日本之旅 变化服饰美臀诱惑模范学院内衣美臀诱惑日本 玛鲁娜女神私房照_秀色女神", "image_num": 41, "album_url": "https://www.xsnvshen.com/album/29747", "index": "030", "harf_link": "https://img.xsnvshen.com/album/20625/29747/"}, "031": {"folder_name": "美臀女神玛鲁娜  性感黑丝OL诱惑秀人网内衣美臀性感诱惑黑丝 玛鲁娜女神私房照_秀色女神", "image_num": 45, "album_url": "https://www.xsnvshen.com/album/29860", "index": "031", "harf_link": "https://img.xsnvshen.com/album/20625/29860/"}, "032": {"folder_name": "[XIUREN]高清写真图 2019.04.08 Manuela玛鲁娜秀人网户外美臀大尺度 玛鲁娜女神私房照_秀色女神", "image_num": 60, "album_url": "https://www.xsnvshen.com/album/30294", "index": "032", "harf_link": "https://img.xsnvshen.com/album/20625/30294/"}, "033": {"folder_name": "[XIUREN]高清写真图 2019.06.11 Manuela玛鲁娜秀人网大尺度 玛鲁娜女神私房照_秀色女神", "image_num": 48, "album_url": "https://www.xsnvshen.com/album/30698", "index": "033", "harf_link": "https://img.xsnvshen.com/album/20625/30698/"}, "034": {"folder_name": "[XIUREN]高清写真图 2019.07.08 Manuela玛鲁娜秀人网美臀内衣 玛鲁娜女神私房照_秀色女神", "image_num": 45, "album_url": "https://www.xsnvshen.com/album/30765", "index": "034", "harf_link": "https://img.xsnvshen.com/album/20625/30765/"}, "035": {"folder_name": "[XIUREN]高清写真图 2019.07.17 Manuela玛鲁娜秀人网运动美臀内衣 玛鲁娜女神私房照_秀色女神", "image_num": 50, "album_url": "https://www.xsnvshen.com/album/30891", "index": "035", "harf_link": "https://img.xsnvshen.com/album/20625/30891/"}, "036": {"folder_name": "[XIUREN]高清写真图 2019.08.01 Manuela玛鲁娜秀人网浴室湿身大尺度 玛鲁娜女神私房照_秀色女神", "image_num": 78, "album_url": "https://www.xsnvshen.com/album/31009", "index": "036", "harf_link": "https://img.xsnvshen.com/album/20625/31009/"}, "037": {"folder_name": "[XIUREN]高清写真图 2019.08.22 Manuela玛鲁娜秀人网旗袍美臀 玛鲁娜女神私房照_秀色女神", "image_num": 53, "album_url": "https://www.xsnvshen.com/album/31166", "index": "037", "harf_link": "https://img.xsnvshen.com/album/20625/31166/"}, "038": {"folder_name": "[XIUREN]高清写真图 2019.10.11 Manuela玛鲁娜秀人网户外校服美臀 玛鲁娜女神私房照_秀色女神", "image_num": 52, "album_url": "https://www.xsnvshen.com/album/31531", "index": "038", "harf_link": "https://img.xsnvshen.com/album/20625/31531/"}, "039": {"folder_name": "[XIUREN]高清写真图 2019.10.28 Manuela玛鲁娜秀人网空姐黑丝美臀 玛鲁娜女神私房照_秀色女神", "image_num": 35, "album_url": "https://www.xsnvshen.com/album/31619", "index": "039", "harf_link": "https://img.xsnvshen.com/album/20625/31619/"}, "040": {"folder_name": "[XIUREN]高清写真图 2019.11.13 Manuela玛鲁娜秀人网双马尾美臀性感清纯 玛鲁娜女神私房照_秀色女神", "image_num": 37, "album_url": "https://www.xsnvshen.com/album/31765", "index": "040", "harf_link": "https://img.xsnvshen.com/album/20625/31765/"}, "041": {"folder_name": "[XIUREN]高清写真图 2019.12.18 Manuela玛鲁娜秀人网内衣美臀性感户外 玛鲁娜女神私房照_秀色女神", "image_num": 44, "album_url": "https://www.xsnvshen.com/album/32117", "index": "041", "harf_link": "https://img.xsnvshen.com/album/20625/32117/"}, "042": {"folder_name": "[XIUREN]高清写真图 2019.12.26 Manuela玛鲁娜秀人网泳池比基尼大尺度性感 玛鲁娜女神私房照_秀色女神", "image_num": 55, "album_url": "https://www.xsnvshen.com/album/32146", "index": "042", "harf_link": "https://img.xsnvshen.com/album/20625/32146/"}, "043": {"folder_name": "[MiStar]高清写真图 2020.01.02 VOL.318 Manuela玛鲁娜魅妍社美臀 玛鲁娜女神私房照_秀色女神", "image_num": 47, "album_url": "https://www.xsnvshen.com/album/32201", "index": "043", "harf_link": "https://img.xsnvshen.com/album/20625/32201/"}, "044": {"folder_name": "[XIUREN]高清写真图 2020.01.13 Manuela玛鲁娜秀人网湿身美臀大尺度 玛鲁娜女神私房照_秀色女神", "image_num": 45, "album_url": "https://www.xsnvshen.com/album/32336", "index": "044", "harf_link": "https://img.xsnvshen.com/album/20625/32336/"}, "045": {"folder_name": "[XIUREN]高清写真图 2020.01.13 Manuela玛鲁娜秀人网户外厨娘美臀大尺度性感 玛鲁娜女神私房照_秀色女神", "image_num": 38, "album_url": "https://www.xsnvshen.com/album/32479", "index": "045", "harf_link": "https://img.xsnvshen.com/album/20625/32479/"}, "046": {"folder_name": "[XIUREN]高清写真图 2020.03.09 玛鲁娜Manuela秀人网美臀性感 玛鲁娜女神私房照_秀色女神", "image_num": 45, "album_url": "https://www.xsnvshen.com/album/32667", "index": "046", "harf_link": "https://img.xsnvshen.com/album/20625/32667/"}, "047": {"folder_name": "[XiuRen]高清写真图 2021.05.12 VOL.3401 玛鲁娜Manuela秀人网秘书美臀黑丝 玛鲁娜女神私房照_秀色女神", "image_num": 75, "album_url": "https://www.xsnvshen.com/album/35998", "index": "047", "harf_link": "https://img.xsnvshen.com/album/20625/35998/"}, "048": {"folder_name": "[XiuRen]高清写真图 2021.11.05 No.4172 Manuela玛鲁娜秀人网美臀 玛鲁娜女神私房照_秀色女神", "image_num": 63, "album_url": "https://www.xsnvshen.com/album/37486", "index": "048", "harf_link": "https://img.xsnvshen.com/album/20625/37486/"}, "049": {"folder_name": "[XiuRen]高清写真图 2021.11.16 No.4223 玛鲁娜Manuela秀人网美臀 玛鲁娜女神私房照_秀色女神", "image_num": 56, "album_url": "https://www.xsnvshen.com/album/37635", "index": "049", "harf_link": "https://img.xsnvshen.com/album/20625/37635/"}, "050": {"folder_name": "[XiuRen]高清写真图 2022.01.07 No.4433 玛鲁娜Manuela秀人网美臀黑丝性感 玛鲁娜女神私房照_秀色女神", "image_num": 47, "album_url": "https://www.xsnvshen.com/album/37970", "index": "050", "harf_link": "https://img.xsnvshen.com/album/20625/37970/"}, "051": {"folder_name": "[XiuRen]高清写真图 2022.01.24 No.4504 玛鲁娜Manuela秀人网女神湿身美臀性感 玛鲁娜女神私房照_秀色女神", "image_num": 61, "album_url": "https://www.xsnvshen.com/album/38085", "index": "051", "harf_link": "https://img.xsnvshen.com/album/20625/38085/"}, "052": {"folder_name": "[XiuRen]高清写真图 2022.03.03 No.4662 玛鲁娜Manuela秀人网女神美臀性感比基尼 玛鲁娜女神私房照_秀色女神", "image_num": 64, "album_url": "https://www.xsnvshen.com/album/38363", "index": "052", "harf_link": "https://img.xsnvshen.com/album/20625/38363/"}, "053": {"folder_name": "[XiuRen]高清写真图 2022.07.26 No.5336 玛鲁娜Manuela秀人网女神成熟美臀性感 玛鲁娜女神私房照_秀色女神", "image_num": 77, "album_url": "https://www.xsnvshen.com/album/39344", "index": "053", "harf_link": "https://img.xsnvshen.com/album/20625/39344/"}, "054": {"folder_name": "[XiuRen]高清写真图 2022.08.02 No.5370 Manuela玛鲁娜秀人网女神泳池比基尼美臀性感 玛鲁娜女神私房照_秀色女神", "image_num": 52, "album_url": "https://www.xsnvshen.com/album/39419", "index": "054", "harf_link": "https://img.xsnvshen.com/album/20625/39419/"}, "055": {"folder_name": "[XiuRen]高清写真图 2022.08.18 No.5457 Manuela玛鲁娜秀人网性感黑丝美臀 玛鲁娜女神私房照_秀色女神", "image_num": 56, "album_url": "https://www.xsnvshen.com/album/39530", "index": "055", "harf_link": "https://img.xsnvshen.com/album/20625/39530/"}, "056": {"folder_name": "[XiuRen]高清写真图 2022.09.09 No.5566 Manuela玛鲁娜秀人网成熟美臀大尺度性感 玛鲁娜女神私房照_秀色女神", "image_num": 65, "album_url": "https://www.xsnvshen.com/album/39565", "index": "056", "harf_link": "https://img.xsnvshen.com/album/20625/39565/"}, "057": {"folder_name": "[XiuRen]高清写真图 2022.10.19 No.5731 玛鲁娜Manuela 三亚旅拍秀人网性感美臀黑丝 玛鲁娜女神私房照_秀色女神", "image_num": 67, "album_url": "https://www.xsnvshen.com/album/40108", "index": "057", "harf_link": "https://img.xsnvshen.com/album/20625/40108/"}, "058": {"folder_name": "[XiuRen]高清写真图 2023.04.11 No.6553 玛鲁娜Manuela 美臀短裙秀人网性感美臀 玛鲁娜女神私房照_秀色女神", "image_num": 42, "album_url": "https://www.xsnvshen.com/album/40855", "index": "058", "harf_link": "https://img.xsnvshen.com/album/20625/40855/"}}}